{
  "products": [
    {
      "id": "1",
      "name": "Product editado",
      "price": 100,
      "stock": 50
    },
    {
      "id": "2",
      "name": "Product 2 editado ",
      "price": 200,
      "stock": 30
    },
    {
      "id": null,
      "name": "Asistente",
      "price": 10000,
      "stock": 5
    },
    {
      "id": null,
      "name": "carne",
      "price": 5000,
      "stock": 3
    },
    {
      "id": "6",
      "name": "Pollo",
      "price": 6000,
      "stock": 4
    },
    {
      "id": "7",
      "name": "queso",
      "price": 15000,
      "stock": 6
    },
    {
      "id": "8",
      "name": "arroz",
      "price": 50000,
      "stock": 8
    },
    {
      "id": "9",
      "name": "lentejas",
      "price": 14000,
      "stock": 40
    }
  ],
  "orders": [
    {
      "id": "1",
      "productId": 1,
      "quantity": 2,
      "total": 200
    },
    {
      "id": "2",
      "productId": 3,
      "quantity": 1,
      "total": 150
    }
  ]
}